LICENSE
MANIFEST.in
README.rst
setup.py
polls/admin.py
polls/apps.py
polls/data_generator.py
polls/models.py
polls/tests.py
polls/urls.py
polls/views.py
polls/migrations/0001_initial.py
polls/migrations/0002_auto_20200826_0014.py
polls/migrations/0003_post_test00.py
polls/migrations/0004_post_test01.py
polls/migrations/0005_delete_post_test01.py
polls/migrations/0006_lecture_subject.py
polls/migrations/0007_auto_20200826_1619.py
polls/migrations/0008_auto_20200826_1938.py
polls/migrations/0009_choice_question.py
polls/migrations/__init__.py
polls/migrations/__pycache__/0001_initial.cpython-38.pyc
polls/migrations/__pycache__/0002_auto_20200826_0014.cpython-38.pyc
polls/migrations/__pycache__/0003_post_test00.cpython-38.pyc
polls/migrations/__pycache__/0004_post_test01.cpython-38.pyc
polls/migrations/__pycache__/0005_delete_post_test01.cpython-38.pyc
polls/migrations/__pycache__/0006_lecture_subject.cpython-38.pyc
polls/migrations/__pycache__/0007_auto_20200826_1619.cpython-38.pyc
polls/migrations/__pycache__/0008_auto_20200826_1938.cpython-38.pyc
polls/migrations/__pycache__/0009_choice_question.cpython-38.pyc
polls/migrations/__pycache__/__init__.cpython-38.pyc
polls/templates/polls/detail.html
polls/templates/polls/index.html
polls_epsilon_deltta.egg-info/PKG-INFO
polls_epsilon_deltta.egg-info/SOURCES.txt
polls_epsilon_deltta.egg-info/dependency_links.txt
polls_epsilon_deltta.egg-info/top_level.txt